mathlib/__init__.py
mathlib/calculations.py
mathlib_test-0.1.1.dist-info/METADATA
mathlib_test-0.1.1.dist-info/WHEEL
mathlib_test-0.1.1.dist-info/RECORD
