Metadata-Version: 2.1
Name: mathlib-test
Version: 0.1.1
Summary: Test math lib
Author-Email: Marcin Pilarczyk <marcinpilarczyk@me.com>
License: MIT
Requires-Python: >=3.7
